{
  "numbers": [
    {
      "id": "5d95",
      "number": 1
    },
    {
      "id": "caa3",
      "number": 2
    },
    {
      "id": "921c",
      "number": 3
    },
    {
      "id": "91c1",
      "number": 4
    },
    {
      "id": "9339",
      "number": 5
    },
    {
      "id": "4e2d",
      "number": 6
    },
    {
      "id": "bc56",
      "number": 7
    },
    {
      "id": "0e6b",
      "number": 8
    }
  ],
  "posts": [
    {
      "id": "1",
      "code": "4OiXq",
      "title": "테스트 진행 글입니다.",
      "content": "글 작성 테스트 진행\n11111111111\n111111111111111111111\n1111111111\n",
      "date": "2025-07-23T08:44:01.146Z",
      "dateString": "2025.7.23 17:44:1"
    },
    {
      "id": "5",
      "code": "NdNJF",
      "title": "테스트 진행222",
      "content": "222222\n22222222222\n22222222",
      "date": "2025-07-26T14:13:19.923Z",
      "dateString": "2025.7.26 23:13:19"
    },
    {
      "id": "6",
      "code": "M53hz",
      "title": "테스트3",
      "content": "333\n333333\n33333\n3수정",
      "date": "2025-07-27T11:32:11.024Z",
      "dateString": "2025.7.27 20:32:11"
    },
    {
      "id": "7",
      "code": "9GtX2",
      "title": "테스트4",
      "content": "44\n444\n44444",
      "date": "2025-07-26T14:25:28.137Z",
      "dateString": "2025.7.26 23:25:28"
    },
    {
      "id": "8",
      "code": "ILd9Z",
      "title": "테스트5",
      "content": "555\n5555\n555555",
      "date": "2025-07-26T14:34:57.835Z",
      "dateString": "2025.7.26 23:34:57"
    }
  ]
}